[
    {
    "id": "G8oVSjLdVcc",
    "des": "Arko ft. Asees Kaur | Zee Music Originals",
    "title": "Pardesi - Sunny Leone",
    "SL": "50"
    },
    {
    "id": "wqupuarNnI0",
    "des": "Habibi (Official Video)| Saajz ft Himanshi Khurana",
    "title": "Habibi (Official Video)| Saajz ft Himanshi Khurana",
    "SL": "49"
    },
    {
    "id": "MsELk83eCwU",
    "des": "Bheegi Bheegi Si Hai Raatein (LYRICS) - Gangster | James, Pritam",
    "title": "Bheegi Bheegi Si Hai Raatein (LYRICS) - Gangster | James, Pritam",
    "SL": "48"
    },
    {
    "id": "3beb3HXqCms",
    "des": "Seedhe Maut - 'Nanchaku' ft MC STΔN",
    "title": "Seedhe Maut - 'Nanchaku' ft MC STΔN",
    "SL": "47"
    },
    {
    "id": "mkj0tK89e9I",
    "des": "Pubg hi khelunga | Pubg Song",
    "title": "Pubg hi khelunga | Pubg Song",
    "SL": "46"
    },
    {
    "id": "jFGKJBPFdUA",
    "des": "Apna Time Aayega | Gully Boy",
    "title": "Apna Time Aayega | Gully Boy",
    "SL": "45"
    },
    {
    "id": "OqO2fu-NjnU",
    "des": "EMIWAY-MERA BHAI MERA BHAI",
    "title": "EMIWAY-MERA BHAI MERA BHAI",
    "SL": "44"
    },
    {
    "id": "1eU7FoXh364",
    "des": "EMIWAY- OUT OF SAMPARK ",
    "title": "EMIWAY- OUT OF SAMPARK ",
    "SL": "43"
    },
    {
    "id": "qcoLCzhLZsI",
    "des": "EMIWAY-KADAK BAN",
    "title": "EMIWAY-KADAK BAN",
    "SL": "42"
    },
    {
    "id": "-IC7qtfhFSw",
    "des": "EMIWAY- #SADAK",
    "title": "EMIWAY- #SADAK",
    "SL": "41"
    },
    {
    "id": "NU3xm6N7tzw",
    "des": "DIVINE - Kaam 25",
    "title": "DIVINE - Kaam 25",
    "SL": "40"
    },
    {
    "id": "KgfKTfJ70zI",
    "des": "Don't Hold Back 2.0 by JACK & JONES FT. Ranveer Singh",
    "title": "Don't Hold Back 2.0 by JACK & JONES FT. Ranveer Singh",
    "SL": "39"
    },
    {
    "id": "ZYu7LcHi84M",
    "des": "MERE BHOLE BABA - PARDHAAN",
    "title": "MERE BHOLE BABA - PARDHAAN",
    "SL": "38"
    },
    {
    "id": "FEvrFe7GWwQ",
    "des": "Roots - DIVINE ft. Raja Kumari",
    "title": "Roots - DIVINE ft. Raja Kumari",
    "SL": "37"
    },
    {
    "id": "qxsQe2EAk40",
    "des": "City Slums - Raja Kumari ft. DIVINE",
    "title": "City Slums - Raja Kumari ft. DIVINE",
    "SL": "36"
    },
    {
    "id": "VNs_cCtdbPc",
    "des": "BROWN MUNDE - AP DHILLON",
    "title": "BROWN MUNDE - AP DHILLON",
    "SL": "35"
    },
    {
    "id": "03L_k4YmPOQ",
    "des": "Akela | Hindi Motivational Rap Song 2020 | Nishayar",
    "title": "Akela | Hindi Motivational Rap Song 2020 | Nishayar",
    "SL": "34"
    },
    {
    "id": "2nBJ_FFQuLI",
    "des": "Mere Rashke Qamar Tu Ne Pehli Nazar",
    "title": "Mere Rashke Qamar Tu Ne Pehli Nazar",
    "SL": "33"
    },
    {
    "id": "95UorB4Gsag",
    "des": "Shrey Singhal (Jahaan Tum Ho)+(Teri Yadein Mulakatein)",
    "title": "Shrey Singhal (Jahaan Tum Ho)+(Teri Yadein Mulakatein)",
    "SL": "32"
    },
    {
    "id": "GtQlQUFyDtk",
    "des": "Aadat (Juda Hoke Bhi) | Atif Aslam ",
    "title": "Aadat (Juda Hoke Bhi) | Atif Aslam ",
    "SL": "31"
    },
    {
    "id": "6iK_D2kRviY",
    "des": "SUNN NA (Official Video) | BALI | RASLA",
    "title": "SUNN NA (Official Video) | BALI | RASLA",
    "SL": "30"
    },
    {
    "id": "zaCbuB3w0kg",
    "des": "EMIWAY - FIRSE MACHAYENGE",
    "title": "EMIWAY - FIRSE MACHAYENGE",
    "SL": "29"
    },
    {
    "id": "AsguumsKgBI",
    "des": "Tera Yaar Hoon Main Video | Sonu Ke Titu Ki Sweety",
    "title": "Tera Yaar Hoon Main Video | Sonu Ke Titu Ki Sweety",
    "SL": "28"
    },
    {
    "id": "OX-h7MtkeOI",
    "des": "O Saathi Video Song | Baaghi 2",
    "title": "O Saathi Video Song | Baaghi 2",
    "SL": "27"
    },
    {
    "id": "wiFOmS6ZvOs",
    "des": "Full Video: Enni Soni ",
    "title": "Full Video: Enni Soni ",
    "SL": "26"
    },
    {
    "id": "CkFZjFyDLTY",
    "des": "Teri Diwani by Ananya Chakrabarti",
    "title": "Teri Diwani by Ananya Chakrabarti",
    "SL": "25"
    },
    {
    "id": "g_IHpBnpzr0",
    "des": "Dilbara Full Video | Pati Patni Aur Woh",
    "title": "Dilbara Full Video | Pati Patni Aur Woh",
    "SL": "24"
    },
    {
    "id": "mQiiw7uRngk",
    "des": "Full Song:Tera Ban Jaunga",
    "title": "Full Song:Tera Ban Jaunga",
    "SL": "23"
    },
    {
    "id": "8v-TWxPWIWc",
    "des": "Humsafar (Full Video) | Varun & Alia Bhatt",
    "title": "Humsafar (Full Video) | Varun & Alia Bhatt",
    "SL": "22"
    },
    {
    "id": "SxTYjptEzZs",
    "des": "Atif Aslam: Pehli Dafa Song ",
    "title": "Atif Aslam: Pehli Dafa Song ",
    "SL": "21"
    },
    {
    "id": "VGPmFSB8qVY",
    "des": "ZERO: Mere Naam Tu Full Song",
    "title": "ZERO: Mere Naam Tu Full Song",
    "SL": "20"
    },
    {
    "id": "K-Ts-NFR62o",
    "des": "JAB TAK Full Video | M.S. DHONI -THE UNTOLD STORY",
    "title": "JAB TAK Full Video | M.S. DHONI -THE UNTOLD STORY",
    "SL": "19"
    },
    {
    "id": "sRaD_vPyqAg",
    "des": "LYRICAL:Dilbara",
    "title": "LYRICAL:Dilbara",
    "SL": "18"
    },
    {
    "id": "eHRrZ5DQCV4",
    "des": "Sunn Raha Hai Na Tu Aashiqui 2 Full Video Song",
    "title": "Sunn Raha Hai Na Tu Aashiqui 2 Full Video Song",
    "SL": "17"
    },
    {
    "id": "hVCYwwFwGEE",
    "des": "Luka Chuppi: Duniyaa Full Video Song",
    "title": "Luka Chuppi: Duniyaa Full Video Song",
    "SL": "16"
    },
    {
    "id": "BTRPBiE_1lA",
    "des": "Full Video:Tu Hi Yaar Mera | Pati Patni Aur Woh",
    "title": "Full Video:Tu Hi Yaar Mera | Pati Patni Aur Woh",
    "SL": "15"
    },
    {
    "id": "xitd9mEZIHk",
    "des": "Mast Magan FULL Video Song",
    "title": "Mast Magan FULL Video Song",
    "SL": "14"
    },
    {
    "id": "xRb8hxwN5zc",
    "des": "AGAR TUM SAATH HO' Full VIDEO song",
    "title": "AGAR TUM SAATH HO' Full VIDEO song",
    "SL": "13"
    },
    {
    "id": "RemShT6JAHw",
    "des": "Tum Hi Aana Full Video | Marjaavaan",
    "title": "Tum Hi Aana Full Video | Marjaavaan",
    "SL": "12"
    },
    {
    "id": "fWQpb6T89d4",
    "des": "Full Video: CHALE AANA | De De Pyaar De",
    "title": "Full Video: CHALE AANA | De De Pyaar De",
    "SL": "11"
    },
    {
    "id": "NzpkclSyDNs",
    "des": "Millind Gaba Zindagi Di Paudi | Bhushan Kumar",
    "title": "Millind Gaba Zindagi Di Paudi | Bhushan Kumar",
    "SL": "10"
    },
    {
    "id": "3KXZduvOfDo",
    "des": "Guru Randhawa: Ishq Tera",
    "title": "Guru Randhawa: Ishq Tera",
    "SL": "9"
    },
    {
    "id": "yFZvQ1Uv358",
    "des": "FULL SONG: Chashni | Bharat | Salman Khan, Katrina Kaif",
    "title": "FULL SONG: Chashni | Bharat | Salman Khan, Katrina Kaif",
    "SL": "8"
    },
    {
    "id": "hejXc_FSYb8",
    "des": "SIMMBA: Tere Bin | Ranveer Singh, Sara Ali Khan",
    "title": "SIMMBA: Tere Bin | Ranveer Singh, Sara Ali Khan",
    "SL": "7"
    },
    {
    "id": "Ydp5fLbxUbk",
    "des": "Atif A: Dekhte Dekhte Song",
    "title": "Atif A: Dekhte Dekhte Song",
    "SL": "6"
    },
    {
    "id": "92J9p0VplTo",
    "des": "Full Song: Tujhe Kitna Chahein Aur",
    "title": "Full Song: Tujhe Kitna Chahein Aur",
    "SL": "5"
    },
    {
    "id": "PVxc5mIHVuQ",
    "des": "Arijit Singh: Pachtaoge | Vicky Kaushal, Nora Fatehi ",
    "title": "Arijit Singh: Pachtaoge | Vicky Kaushal, Nora Fatehi ",
    "SL": "4"
    },
    {
    "id": "MRtRcTfszjY",
    "des": "Soch Na Sake FULL VIDEO SONG",
    "title": "Soch Na Sake FULL VIDEO SONG",
    "SL": "3"
    },
    {
    "id": "IJq0yyWug1k",
    "des": "\"\"\"Tum Hi Ho Aashiqui 2\"\" Full Video Song\"",
    "title": "\"\"\"Tum Hi Ho Aashiqui 2\"\" Full Video Song\"",
    "SL": "2"
    },
    {
    "id": "Ps4aVpIESkc",
    "des": "ARIJIT SINGH VERSION: Bekhayali Full Song",
    "title": "ARIJIT SINGH VERSION: Bekhayali Full Song",
    "SL": "1"
    }
    ]